setup.py
src/number_to_word_beastboi/__init__.py
src/number_to_word_beastboi/num2words_mydna.py
num2words_bydna-0.0.1.dist-info/METADATA
num2words_bydna-0.0.1.dist-info/WHEEL
num2words_bydna-0.0.1.dist-info/licenses/LICENSE.txt
num2words_bydna-0.0.1.dist-info/RECORD
