Metadata-Version: 2.1
Name: num2words_bydna
Version: 0.0.1
Summary: A small module for converting numbers to words
Project-URL: Homepage, https://github.com/beastboixdna
Project-URL: Bug Tracker, https://github.com/pypa/sampleproject/issues
Author-email: Beast Boi <beastboigithub89@gmail.com>
License-File: LICENSE.txt
Classifier: License :: OSI Approved :: MIT License
Classifier: Operating System :: OS Independent
Classifier: Programming Language :: Python :: 3
Requires-Python: >=3.7
